{
  "initial_balance": 1000.0,
  "final_balance": 999.7099999999999,
  "profit": -0.2900000000000773,
  "profit_percentage": -0.02900000000000773,
  "total_trades": 50,
  "win_rate": 30.0,
  "max_drawdown_pct": 1.0156648306059084,
  "trades": [
    {
      "entry_price": 139.36,
      "exit_price": 138.85,
      "entry_price_effective": 139.36,
      "exit_price_effective": 138.85,
      "entry_fee": 0.0,
      "exit_fee": 0.0,
      "gross_pnl": -0.5100000000000193,
      "net_pnl": -0.5100000000000193,
      "exit_reason": "SELL",
      "entry_index": "2025-12-12 12:45:00+00:00",
      "exit_index": "2025-12-12 13:50:00+00:00"
    },
    {
      "entry_price": 133.0,
      "exit_price": 132.2,
      "entry_price_effective": 133.0,
      "exit_price_effective": 132.2,
      "entry_fee": 0.0,
      "exit_fee": 0.0,
      "gross_pnl": -0.8000000000000114,
      "net_pnl": -0.8000000000000114,
      "exit_reason": "SL",
      "entry_index": "2025-12-12 18:50:00+00:00",
      "exit_index": "2025-12-12 19:05:00+00:00"
    },
    {
      "entry_price": 131.79,
      "exit_price": 132.35,
      "entry_price_effective": 131.79,
      "exit_price_effective": 132.35,
      "entry_fee": 0.0,
      "exit_fee": 0.0,
      "gross_pnl": 0.5600000000000023,
      "net_pnl": 0.5600000000000023,
      "exit_reason": "SELL",
      "entry_index": "2025-12-12 21:40:00+00:00",
      "exit_index": "2025-12-13 00:25:00+00:00"
    },
    {
      "entry_price": 132.57,
      "exit_price": 132.51,
      "entry_price_effective": 132.57,
      "exit_price_effective": 132.51,
      "entry_fee": 0.0,
      "exit_fee": 0.0,
      "gross_pnl": -0.060000000000002274,
      "net_pnl": -0.060000000000002274,
      "exit_reason": "SELL",
      "entry_index": "2025-12-13 00:30:00+00:00",
      "exit_index": "2025-12-13 01:50:00+00:00"
    },
    {
      "entry_price": 132.6,
      "exit_price": 132.56,
      "entry_price_effective": 132.6,
      "exit_price_effective": 132.56,
      "entry_fee": 0.0,
      "exit_fee": 0.0,
      "gross_pnl": -0.03999999999999204,
      "net_pnl": -0.03999999999999204,
      "exit_reason": "SELL",
      "entry_index": "2025-12-13 01:55:00+00:00",
      "exit_index": "2025-12-13 02:55:00+00:00"
    },
    {
      "entry_price": 132.74,
      "exit_price": 132.62,
      "entry_price_effective": 132.74,
      "exit_price_effective": 132.62,
      "entry_fee": 0.0,
      "exit_fee": 0.0,
      "gross_pnl": -0.12000000000000455,
      "net_pnl": -0.12000000000000455,
      "exit_reason": "SELL",
      "entry_index": "2025-12-13 03:15:00+00:00",
      "exit_index": "2025-12-13 04:30:00+00:00"
    },
    {
      "entry_price": 132.75,
      "exit_price": 132.63,
      "entry_price_effective": 132.75,
      "exit_price_effective": 132.63,
      "entry_fee": 0.0,
      "exit_fee": 0.0,
      "gross_pnl": -0.12000000000000455,
      "net_pnl": -0.12000000000000455,
      "exit_reason": "SELL",
      "entry_index": "2025-12-13 04:40:00+00:00",
      "exit_index": "2025-12-13 05:25:00+00:00"
    },
    {
      "entry_price": 132.76,
      "exit_price": 133.56,
      "entry_price_effective": 132.76,
      "exit_price_effective": 133.56,
      "entry_fee": 0.0,
      "exit_fee": 0.0,
      "gross_pnl": 0.8000000000000114,
      "net_pnl": 0.8000000000000114,
      "exit_reason": "SELL",
      "entry_index": "2025-12-13 06:50:00+00:00",
      "exit_index": "2025-12-13 11:30:00+00:00"
    },
    {
      "entry_price": 133.16,
      "exit_price": 132.96,
      "entry_price_effective": 133.16,
      "exit_price_effective": 132.96,
      "entry_fee": 0.0,
      "exit_fee": 0.0,
      "gross_pnl": -0.19999999999998863,
      "net_pnl": -0.19999999999998863,
      "exit_reason": "SELL",
      "entry_index": "2025-12-13 14:15:00+00:00",
      "exit_index": "2025-12-13 14:20:00+00:00"
    },
    {
      "entry_price": 133.14,
      "exit_price": 133.01,
      "entry_price_effective": 133.14,
      "exit_price_effective": 133.01,
      "entry_fee": 0.0,
      "exit_fee": 0.0,
      "gross_pnl": -0.12999999999999545,
      "net_pnl": -0.12999999999999545,
      "exit_reason": "SELL",
      "entry_index": "2025-12-13 14:50:00+00:00",
      "exit_index": "2025-12-13 16:25:00+00:00"
    },
    {
      "entry_price": 132.66,
      "exit_price": 132.26,
      "entry_price_effective": 132.66,
      "exit_price_effective": 132.26,
      "entry_fee": 0.0,
      "exit_fee": 0.0,
      "gross_pnl": -0.4000000000000057,
      "net_pnl": -0.4000000000000057,
      "exit_reason": "SELL",
      "entry_index": "2025-12-13 19:35:00+00:00",
      "exit_index": "2025-12-13 20:50:00+00:00"
    },
    {
      "entry_price": 132.58,
      "exit_price": 132.22,
      "entry_price_effective": 132.58,
      "exit_price_effective": 132.22,
      "entry_fee": 0.0,
      "exit_fee": 0.0,
      "gross_pnl": -0.36000000000001364,
      "net_pnl": -0.36000000000001364,
      "exit_reason": "SELL",
      "entry_index": "2025-12-13 22:05:00+00:00",
      "exit_index": "2025-12-13 22:10:00+00:00"
    },
    {
      "entry_price": 132.4,
      "exit_price": 133.12,
      "entry_price_effective": 132.4,
      "exit_price_effective": 133.12,
      "entry_fee": 0.0,
      "exit_fee": 0.0,
      "gross_pnl": 0.7199999999999989,
      "net_pnl": 0.7199999999999989,
      "exit_reason": "SELL",
      "entry_index": "2025-12-13 22:20:00+00:00",
      "exit_index": "2025-12-14 03:10:00+00:00"
    },
    {
      "entry_price": 132.79,
      "exit_price": 132.87,
      "entry_price_effective": 132.79,
      "exit_price_effective": 132.87,
      "entry_fee": 0.0,
      "exit_fee": 0.0,
      "gross_pnl": 0.0800000000000125,
      "net_pnl": 0.0800000000000125,
      "exit_reason": "SELL",
      "entry_index": "2025-12-14 06:15:00+00:00",
      "exit_index": "2025-12-14 08:50:00+00:00"
    },
    {
      "entry_price": 131.61,
      "exit_price": 131.28,
      "entry_price_effective": 131.61,
      "exit_price_effective": 131.28,
      "entry_fee": 0.0,
      "exit_fee": 0.0,
      "gross_pnl": -0.3300000000000125,
      "net_pnl": -0.3300000000000125,
      "exit_reason": "SELL",
      "entry_index": "2025-12-14 12:50:00+00:00",
      "exit_index": "2025-12-14 12:55:00+00:00"
    },
    {
      "entry_price": 131.49,
      "exit_price": 130.8,
      "entry_price_effective": 131.49,
      "exit_price_effective": 130.8,
      "entry_fee": 0.0,
      "exit_fee": 0.0,
      "gross_pnl": -0.6899999999999977,
      "net_pnl": -0.6899999999999977,
      "exit_reason": "SL",
      "entry_index": "2025-12-14 14:00:00+00:00",
      "exit_index": "2025-12-14 14:30:00+00:00"
    },
    {
      "entry_price": 131.28,
      "exit_price": 130.58,
      "entry_price_effective": 131.28,
      "exit_price_effective": 130.58,
      "entry_fee": 0.0,
      "exit_fee": 0.0,
      "gross_pnl": -0.6999999999999886,
      "net_pnl": -0.6999999999999886,
      "exit_reason": "SL",
      "entry_index": "2025-12-14 16:25:00+00:00",
      "exit_index": "2025-12-14 16:40:00+00:00"
    },
    {
      "entry_price": 130.86,
      "exit_price": 129.8,
      "entry_price_effective": 130.86,
      "exit_price_effective": 129.8,
      "entry_fee": 0.0,
      "exit_fee": 0.0,
      "gross_pnl": -1.0600000000000023,
      "net_pnl": -1.0600000000000023,
      "exit_reason": "SL",
      "entry_index": "2025-12-14 16:50:00+00:00",
      "exit_index": "2025-12-14 17:10:00+00:00"
    },
    {
      "entry_price": 130.54,
      "exit_price": 130.1,
      "entry_price_effective": 130.54,
      "exit_price_effective": 130.1,
      "entry_fee": 0.0,
      "exit_fee": 0.0,
      "gross_pnl": -0.4399999999999977,
      "net_pnl": -0.4399999999999977,
      "exit_reason": "SELL",
      "entry_index": "2025-12-14 18:55:00+00:00",
      "exit_index": "2025-12-14 19:10:00+00:00"
    },
    {
      "entry_price": 130.55,
      "exit_price": 130.08,
      "entry_price_effective": 130.55,
      "exit_price_effective": 130.08,
      "entry_fee": 0.0,
      "exit_fee": 0.0,
      "gross_pnl": -0.46999999999999886,
      "net_pnl": -0.46999999999999886,
      "exit_reason": "SELL",
      "entry_index": "2025-12-14 20:10:00+00:00",
      "exit_index": "2025-12-14 20:25:00+00:00"
    },
    {
      "entry_price": 130.19,
      "exit_price": 129.4,
      "entry_price_effective": 130.19,
      "exit_price_effective": 129.4,
      "entry_fee": 0.0,
      "exit_fee": 0.0,
      "gross_pnl": -0.789999999999992,
      "net_pnl": -0.789999999999992,
      "exit_reason": "SL",
      "entry_index": "2025-12-15 00:20:00+00:00",
      "exit_index": "2025-12-15 00:35:00+00:00"
    },
    {
      "entry_price": 129.84,
      "exit_price": 131.13,
      "entry_price_effective": 129.84,
      "exit_price_effective": 131.13,
      "entry_fee": 0.0,
      "exit_fee": 0.0,
      "gross_pnl": 1.289999999999992,
      "net_pnl": 1.289999999999992,
      "exit_reason": "SELL",
      "entry_index": "2025-12-15 00:50:00+00:00",
      "exit_index": "2025-12-15 03:40:00+00:00"
    },
    {
      "entry_price": 131.57,
      "exit_price": 132.07,
      "entry_price_effective": 131.57,
      "exit_price_effective": 132.07,
      "entry_fee": 0.0,
      "exit_fee": 0.0,
      "gross_pnl": 0.5,
      "net_pnl": 0.5,
      "exit_reason": "SELL",
      "entry_index": "2025-12-15 04:40:00+00:00",
      "exit_index": "2025-12-15 11:40:00+00:00"
    },
    {
      "entry_price": 132.91,
      "exit_price": 132.12,
      "entry_price_effective": 132.91,
      "exit_price_effective": 132.12,
      "entry_fee": 0.0,
      "exit_fee": 0.0,
      "gross_pnl": -0.789999999999992,
      "net_pnl": -0.789999999999992,
      "exit_reason": "SL",
      "entry_index": "2025-12-15 12:35:00+00:00",
      "exit_index": "2025-12-15 13:00:00+00:00"
    },
    {
      "entry_price": 132.65,
      "exit_price": 131.65,
      "entry_price_effective": 132.65,
      "exit_price_effective": 131.65,
      "entry_fee": 0.0,
      "exit_fee": 0.0,
      "gross_pnl": -1.0,
      "net_pnl": -1.0,
      "exit_reason": "SL",
      "entry_index": "2025-12-15 13:10:00+00:00",
      "exit_index": "2025-12-15 14:45:00+00:00"
    },
    {
      "entry_price": 125.7,
      "exit_price": 124.93,
      "entry_price_effective": 125.7,
      "exit_price_effective": 124.93,
      "entry_fee": 0.0,
      "exit_fee": 0.0,
      "gross_pnl": -0.769999999999996,
      "net_pnl": -0.769999999999996,
      "exit_reason": "SL",
      "entry_index": "2025-12-15 19:30:00+00:00",
      "exit_index": "2025-12-15 19:55:00+00:00"
    },
    {
      "entry_price": 125.28,
      "exit_price": 126.14,
      "entry_price_effective": 125.28,
      "exit_price_effective": 126.14,
      "entry_fee": 0.0,
      "exit_fee": 0.0,
      "gross_pnl": 0.8599999999999994,
      "net_pnl": 0.8599999999999994,
      "exit_reason": "SELL",
      "entry_index": "2025-12-15 20:50:00+00:00",
      "exit_index": "2025-12-16 00:55:00+00:00"
    },
    {
      "entry_price": 127.09,
      "exit_price": 126.28,
      "entry_price_effective": 127.09,
      "exit_price_effective": 126.28,
      "entry_fee": 0.0,
      "exit_fee": 0.0,
      "gross_pnl": -0.8100000000000023,
      "net_pnl": -0.8100000000000023,
      "exit_reason": "SL",
      "entry_index": "2025-12-16 02:25:00+00:00",
      "exit_index": "2025-12-16 03:05:00+00:00"
    },
    {
      "entry_price": 126.13,
      "exit_price": 126.27,
      "entry_price_effective": 126.13,
      "exit_price_effective": 126.27,
      "entry_fee": 0.0,
      "exit_fee": 0.0,
      "gross_pnl": 0.14000000000000057,
      "net_pnl": 0.14000000000000057,
      "exit_reason": "SELL",
      "entry_index": "2025-12-16 05:20:00+00:00",
      "exit_index": "2025-12-16 07:35:00+00:00"
    },
    {
      "entry_price": 126.22,
      "exit_price": 127.64,
      "entry_price_effective": 126.22,
      "exit_price_effective": 127.64,
      "entry_fee": 0.0,
      "exit_fee": 0.0,
      "gross_pnl": 1.4200000000000017,
      "net_pnl": 1.4200000000000017,
      "exit_reason": "SELL",
      "entry_index": "2025-12-16 09:35:00+00:00",
      "exit_index": "2025-12-16 13:35:00+00:00"
    },
    {
      "entry_price": 128.74,
      "exit_price": 127.91,
      "entry_price_effective": 128.74,
      "exit_price_effective": 127.91,
      "entry_fee": 0.0,
      "exit_fee": 0.0,
      "gross_pnl": -0.8300000000000125,
      "net_pnl": -0.8300000000000125,
      "exit_reason": "SL",
      "entry_index": "2025-12-16 14:30:00+00:00",
      "exit_index": "2025-12-16 15:00:00+00:00"
    },
    {
      "entry_price": 128.29,
      "exit_price": 128.05,
      "entry_price_effective": 128.29,
      "exit_price_effective": 128.05,
      "entry_fee": 0.0,
      "exit_fee": 0.0,
      "gross_pnl": -0.23999999999998067,
      "net_pnl": -0.23999999999998067,
      "exit_reason": "SELL",
      "entry_index": "2025-12-16 15:40:00+00:00",
      "exit_index": "2025-12-16 16:40:00+00:00"
    },
    {
      "entry_price": 128.22,
      "exit_price": 127.36,
      "entry_price_effective": 128.22,
      "exit_price_effective": 127.36,
      "entry_fee": 0.0,
      "exit_fee": 0.0,
      "gross_pnl": -0.8599999999999994,
      "net_pnl": -0.8599999999999994,
      "exit_reason": "SL",
      "entry_index": "2025-12-16 18:50:00+00:00",
      "exit_index": "2025-12-16 19:00:00+00:00"
    },
    {
      "entry_price": 127.83,
      "exit_price": 128.33,
      "entry_price_effective": 127.83,
      "exit_price_effective": 128.33,
      "entry_fee": 0.0,
      "exit_fee": 0.0,
      "gross_pnl": 0.5000000000000142,
      "net_pnl": 0.5000000000000142,
      "exit_reason": "SELL",
      "entry_index": "2025-12-16 20:00:00+00:00",
      "exit_index": "2025-12-17 00:30:00+00:00"
    },
    {
      "entry_price": 128.88,
      "exit_price": 128.68,
      "entry_price_effective": 128.88,
      "exit_price_effective": 128.68,
      "entry_fee": 0.0,
      "exit_fee": 0.0,
      "gross_pnl": -0.19999999999998863,
      "net_pnl": -0.19999999999998863,
      "exit_reason": "SELL",
      "entry_index": "2025-12-17 00:50:00+00:00",
      "exit_index": "2025-12-17 02:15:00+00:00"
    },
    {
      "entry_price": 129.25,
      "exit_price": 128.51,
      "entry_price_effective": 129.25,
      "exit_price_effective": 128.51,
      "entry_fee": 0.0,
      "exit_fee": 0.0,
      "gross_pnl": -0.7400000000000091,
      "net_pnl": -0.7400000000000091,
      "exit_reason": "SL",
      "entry_index": "2025-12-17 02:45:00+00:00",
      "exit_index": "2025-12-17 03:35:00+00:00"
    },
    {
      "entry_price": 127.81,
      "exit_price": 127.59,
      "entry_price_effective": 127.81,
      "exit_price_effective": 127.59,
      "entry_fee": 0.0,
      "exit_fee": 0.0,
      "gross_pnl": -0.21999999999999886,
      "net_pnl": -0.21999999999999886,
      "exit_reason": "SELL",
      "entry_index": "2025-12-17 06:25:00+00:00",
      "exit_index": "2025-12-17 06:40:00+00:00"
    },
    {
      "entry_price": 127.88,
      "exit_price": 127.61,
      "entry_price_effective": 127.88,
      "exit_price_effective": 127.61,
      "entry_fee": 0.0,
      "exit_fee": 0.0,
      "gross_pnl": -0.269999999999996,
      "net_pnl": -0.269999999999996,
      "exit_reason": "SELL",
      "entry_index": "2025-12-17 07:00:00+00:00",
      "exit_index": "2025-12-17 07:15:00+00:00"
    },
    {
      "entry_price": 127.87,
      "exit_price": 127.42,
      "entry_price_effective": 127.87,
      "exit_price_effective": 127.42,
      "entry_fee": 0.0,
      "exit_fee": 0.0,
      "gross_pnl": -0.45000000000000284,
      "net_pnl": -0.45000000000000284,
      "exit_reason": "SELL",
      "entry_index": "2025-12-17 07:20:00+00:00",
      "exit_index": "2025-12-17 08:20:00+00:00"
    },
    {
      "entry_price": 127.22,
      "exit_price": 126.98,
      "entry_price_effective": 127.22,
      "exit_price_effective": 126.98,
      "entry_fee": 0.0,
      "exit_fee": 0.0,
      "gross_pnl": -0.23999999999999488,
      "net_pnl": -0.23999999999999488,
      "exit_reason": "SELL",
      "entry_index": "2025-12-17 11:10:00+00:00",
      "exit_index": "2025-12-17 15:50:00+00:00"
    },
    {
      "entry_price": 123.37,
      "exit_price": 122.71,
      "entry_price_effective": 123.37,
      "exit_price_effective": 122.71,
      "entry_fee": 0.0,
      "exit_fee": 0.0,
      "gross_pnl": -0.6600000000000108,
      "net_pnl": -0.6600000000000108,
      "exit_reason": "SL",
      "entry_index": "2025-12-17 20:20:00+00:00",
      "exit_index": "2025-12-17 21:05:00+00:00"
    },
    {
      "entry_price": 122.86,
      "exit_price": 123.12,
      "entry_price_effective": 122.86,
      "exit_price_effective": 123.12,
      "entry_fee": 0.0,
      "exit_fee": 0.0,
      "gross_pnl": 0.2600000000000051,
      "net_pnl": 0.2600000000000051,
      "exit_reason": "SELL",
      "entry_index": "2025-12-17 22:25:00+00:00",
      "exit_index": "2025-12-18 03:25:00+00:00"
    },
    {
      "entry_price": 124.02,
      "exit_price": 123.31,
      "entry_price_effective": 124.02,
      "exit_price_effective": 123.31,
      "entry_fee": 0.0,
      "exit_fee": 0.0,
      "gross_pnl": -0.7099999999999937,
      "net_pnl": -0.7099999999999937,
      "exit_reason": "SL",
      "entry_index": "2025-12-18 04:00:00+00:00",
      "exit_index": "2025-12-18 05:05:00+00:00"
    },
    {
      "entry_price": 123.01,
      "exit_price": 122.68,
      "entry_price_effective": 123.01,
      "exit_price_effective": 122.68,
      "entry_fee": 0.0,
      "exit_fee": 0.0,
      "gross_pnl": -0.3299999999999983,
      "net_pnl": -0.3299999999999983,
      "exit_reason": "SELL",
      "entry_index": "2025-12-18 07:15:00+00:00",
      "exit_index": "2025-12-18 07:50:00+00:00"
    },
    {
      "entry_price": 123.24,
      "exit_price": 122.67,
      "entry_price_effective": 123.24,
      "exit_price_effective": 122.67,
      "entry_fee": 0.0,
      "exit_fee": 0.0,
      "gross_pnl": -0.5699999999999932,
      "net_pnl": -0.5699999999999932,
      "exit_reason": "SELL",
      "entry_index": "2025-12-18 08:20:00+00:00",
      "exit_index": "2025-12-18 09:10:00+00:00"
    },
    {
      "entry_price": 123.08,
      "exit_price": 123.41,
      "entry_price_effective": 123.08,
      "exit_price_effective": 123.41,
      "entry_fee": 0.0,
      "exit_fee": 0.0,
      "gross_pnl": 0.3299999999999983,
      "net_pnl": 0.3299999999999983,
      "exit_reason": "SELL",
      "entry_index": "2025-12-18 09:20:00+00:00",
      "exit_index": "2025-12-18 11:25:00+00:00"
    },
    {
      "entry_price": 123.87,
      "exit_price": 126.43,
      "entry_price_effective": 123.87,
      "exit_price_effective": 126.43,
      "entry_fee": 0.0,
      "exit_fee": 0.0,
      "gross_pnl": 2.5600000000000023,
      "net_pnl": 2.5600000000000023,
      "exit_reason": "SELL",
      "entry_index": "2025-12-18 11:45:00+00:00",
      "exit_index": "2025-12-18 16:30:00+00:00"
    },
    {
      "entry_price": 127.02,
      "exit_price": 126.24,
      "entry_price_effective": 127.02,
      "exit_price_effective": 126.24,
      "entry_fee": 0.0,
      "exit_fee": 0.0,
      "gross_pnl": -0.7800000000000011,
      "net_pnl": -0.7800000000000011,
      "exit_reason": "SL",
      "entry_index": "2025-12-18 16:35:00+00:00",
      "exit_index": "2025-12-18 17:00:00+00:00"
    },
    {
      "entry_price": 119.3,
      "exit_price": 119.35,
      "entry_price_effective": 119.3,
      "exit_price_effective": 119.35,
      "entry_fee": 0.0,
      "exit_fee": 0.0,
      "gross_pnl": 0.04999999999999716,
      "net_pnl": 0.04999999999999716,
      "exit_reason": "SELL",
      "entry_index": "2025-12-18 21:45:00+00:00",
      "exit_index": "2025-12-19 00:20:00+00:00"
    },
    {
      "entry_price": 118.59,
      "exit_price": 125.92,
      "entry_price_effective": 118.59,
      "exit_price_effective": 125.92,
      "entry_fee": 0.0,
      "exit_fee": 0.0,
      "gross_pnl": 7.329999999999998,
      "net_pnl": 7.329999999999998,
      "exit_reason": "LAST",
      "entry_index": "2025-12-19 02:40:00+00:00",
      "exit_index": "2025-12-19 12:35:00+00:00"
    }
  ],
  "aborted_early": false,
  "insufficient_trades": false,
  "min_trades_required": 0
}